{
    "bounds": {
        "left": 0,
        "right": 62,
        "top": 0,
        "bottom": 40
    },
    "points": [
        {
            "x": 47,
            "y": 0
        },
        {
            "x": 45,
            "y": 1
        },
        {
            "x": 46,
            "y": 1
        },
        {
            "x": 47,
            "y": 1
        },
        {
            "x": 44,
            "y": 2
        },
        {
            "x": 44,
            "y": 3
        },
        {
            "x": 45,
            "y": 3
        },
        {
            "x": 50,
            "y": 3
        },
        {
            "x": 51,
            "y": 3
        },
        {
            "x": 16,
            "y": 4
        },
        {
            "x": 17,
            "y": 4
        },
        {
            "x": 50,
            "y": 4
        },
        {
            "x": 16,
            "y": 5
        },
        {
            "x": 17,
            "y": 5
        },
        {
            "x": 33,
            "y": 5
        },
        {
            "x": 48,
            "y": 5
        },
        {
            "x": 50,
            "y": 5
        },
        {
            "x": 33,
            "y": 6
        },
        {
            "x": 34,
            "y": 6
        },
        {
            "x": 35,
            "y": 6
        },
        {
            "x": 48,
            "y": 6
        },
        {
            "x": 49,
            "y": 6
        },
        {
            "x": 36,
            "y": 7
        },
        {
            "x": 9,
            "y": 8
        },
        {
            "x": 10,
            "y": 8
        },
        {
            "x": 26,
            "y": 8
        },
        {
            "x": 27,
            "y": 8
        },
        {
            "x": 35,
            "y": 8
        },
        {
            "x": 10,
            "y": 9
        },
        {
            "x": 26,
            "y": 9
        },
        {
            "x": 34,
            "y": 9
        },
        {
            "x": 10,
            "y": 10
        },
        {
            "x": 12,
            "y": 10
        },
        {
            "x": 24,
            "y": 10
        },
        {
            "x": 26,
            "y": 10
        },
        {
            "x": 34,
            "y": 10
        },
        {
            "x": 35,
            "y": 10
        },
        {
            "x": 11,
            "y": 11
        },
        {
            "x": 12,
            "y": 11
        },
        {
            "x": 24,
            "y": 11
        },
        {
            "x": 25,
            "y": 11
        },
        {
            "x": 5,
            "y": 12
        },
        {
            "x": 5,
            "y": 13
        },
        {
            "x": 6,
            "y": 13
        },
        {
            "x": 7,
            "y": 13
        },
        {
            "x": 8,
            "y": 14
        },
        {
            "x": 55,
            "y": 14
        },
        {
            "x": 56,
            "y": 14
        },
        {
            "x": 7,
            "y": 15
        },
        {
            "x": 8,
            "y": 15
        },
        {
            "x": 54,
            "y": 15
        },
        {
            "x": 57,
            "y": 15
        },
        {
            "x": 26,
            "y": 16
        },
        {
            "x": 53,
            "y": 16
        },
        {
            "x": 54,
            "y": 16
        },
        {
            "x": 55,
            "y": 16
        },
        {
            "x": 56,
            "y": 16
        },
        {
            "x": 57,
            "y": 16
        },
        {
            "x": 58,
            "y": 16
        },
        {
            "x": 0,
            "y": 17
        },
        {
            "x": 1,
            "y": 17
        },
        {
            "x": 26,
            "y": 17
        },
        {
            "x": 37,
            "y": 17
        },
        {
            "x": 41,
            "y": 17
        },
        {
            "x": 42,
            "y": 17
        },
        {
            "x": 43,
            "y": 17
        },
        {
            "x": 54,
            "y": 17
        },
        {
            "x": 57,
            "y": 17
        },
        {
            "x": 1,
            "y": 18
        },
        {
            "x": 36,
            "y": 18
        },
        {
            "x": 38,
            "y": 18
        },
        {
            "x": 43,
            "y": 18
        },
        {
            "x": 55,
            "y": 18
        },
        {
            "x": 56,
            "y": 18
        },
        {
            "x": 1,
            "y": 19
        },
        {
            "x": 3,
            "y": 19
        },
        {
            "x": 35,
            "y": 19
        },
        {
            "x": 38,
            "y": 19
        },
        {
            "x": 41,
            "y": 19
        },
        {
            "x": 42,
            "y": 19
        },
        {
            "x": 43,
            "y": 19
        },
        {
            "x": 2,
            "y": 20
        },
        {
            "x": 3,
            "y": 20
        },
        {
            "x": 25,
            "y": 20
        },
        {
            "x": 26,
            "y": 20
        },
        {
            "x": 36,
            "y": 20
        },
        {
            "x": 37,
            "y": 20
        },
        {
            "x": 59,
            "y": 20
        },
        {
            "x": 60,
            "y": 20
        },
        {
            "x": 19,
            "y": 21
        },
        {
            "x": 20,
            "y": 21
        },
        {
            "x": 21,
            "y": 21
        },
        {
            "x": 24,
            "y": 21
        },
        {
            "x": 27,
            "y": 21
        },
        {
            "x": 59,
            "y": 21
        },
        {
            "x": 61,
            "y": 21
        },
        {
            "x": 6,
            "y": 22
        },
        {
            "x": 7,
            "y": 22
        },
        {
            "x": 19,
            "y": 22
        },
        {
            "x": 24,
            "y": 22
        },
        {
            "x": 26,
            "y": 22
        },
        {
            "x": 61,
            "y": 22
        },
        {
            "x": 5,
            "y": 23
        },
        {
            "x": 8,
            "y": 23
        },
        {
            "x": 19,
            "y": 23
        },
        {
            "x": 20,
            "y": 23
        },
        {
            "x": 21,
            "y": 23
        },
        {
            "x": 25,
            "y": 23
        },
        {
            "x": 36,
            "y": 23
        },
        {
            "x": 61,
            "y": 23
        },
        {
            "x": 62,
            "y": 23
        },
        {
            "x": 4,
            "y": 24
        },
        {
            "x": 5,
            "y": 24
        },
        {
            "x": 6,
            "y": 24
        },
        {
            "x": 7,
            "y": 24
        },
        {
            "x": 8,
            "y": 24
        },
        {
            "x": 9,
            "y": 24
        },
        {
            "x": 36,
            "y": 24
        },
        {
            "x": 5,
            "y": 25
        },
        {
            "x": 8,
            "y": 25
        },
        {
            "x": 54,
            "y": 25
        },
        {
            "x": 55,
            "y": 25
        },
        {
            "x": 6,
            "y": 26
        },
        {
            "x": 7,
            "y": 26
        },
        {
            "x": 54,
            "y": 26
        },
        {
            "x": 55,
            "y": 27
        },
        {
            "x": 56,
            "y": 27
        },
        {
            "x": 57,
            "y": 27
        },
        {
            "x": 57,
            "y": 28
        },
        {
            "x": 37,
            "y": 29
        },
        {
            "x": 38,
            "y": 29
        },
        {
            "x": 50,
            "y": 29
        },
        {
            "x": 51,
            "y": 29
        },
        {
            "x": 27,
            "y": 30
        },
        {
            "x": 28,
            "y": 30
        },
        {
            "x": 36,
            "y": 30
        },
        {
            "x": 38,
            "y": 30
        },
        {
            "x": 50,
            "y": 30
        },
        {
            "x": 52,
            "y": 30
        },
        {
            "x": 28,
            "y": 31
        },
        {
            "x": 36,
            "y": 31
        },
        {
            "x": 52,
            "y": 31
        },
        {
            "x": 27,
            "y": 32
        },
        {
            "x": 35,
            "y": 32
        },
        {
            "x": 36,
            "y": 32
        },
        {
            "x": 52,
            "y": 32
        },
        {
            "x": 53,
            "y": 32
        },
        {
            "x": 26,
            "y": 33
        },
        {
            "x": 13,
            "y": 34
        },
        {
            "x": 14,
            "y": 34
        },
        {
            "x": 27,
            "y": 34
        },
        {
            "x": 28,
            "y": 34
        },
        {
            "x": 29,
            "y": 34
        },
        {
            "x": 12,
            "y": 35
        },
        {
            "x": 14,
            "y": 35
        },
        {
            "x": 29,
            "y": 35
        },
        {
            "x": 45,
            "y": 35
        },
        {
            "x": 46,
            "y": 35
        },
        {
            "x": 12,
            "y": 36
        },
        {
            "x": 45,
            "y": 36
        },
        {
            "x": 46,
            "y": 36
        },
        {
            "x": 11,
            "y": 37
        },
        {
            "x": 12,
            "y": 37
        },
        {
            "x": 17,
            "y": 37
        },
        {
            "x": 18,
            "y": 37
        },
        {
            "x": 18,
            "y": 38
        },
        {
            "x": 15,
            "y": 39
        },
        {
            "x": 16,
            "y": 39
        },
        {
            "x": 17,
            "y": 39
        },
        {
            "x": 15,
            "y": 40
        }
    ]
}