{
    "bounds": {
        "left": 0,
        "right": 37,
        "top": 0,
        "bottom": 41
    },
    "points": [
        {
            "x": 2,
            "y": 0
        },
        {
            "x": 2,
            "y": 1
        },
        {
            "x": 1,
            "y": 2
        },
        {
            "x": 3,
            "y": 2
        },
        {
            "x": 2,
            "y": 3
        },
        {
            "x": 24,
            "y": 3
        },
        {
            "x": 2,
            "y": 4
        },
        {
            "x": 22,
            "y": 4
        },
        {
            "x": 23,
            "y": 4
        },
        {
            "x": 24,
            "y": 4
        },
        {
            "x": 2,
            "y": 5
        },
        {
            "x": 21,
            "y": 5
        },
        {
            "x": 2,
            "y": 6
        },
        {
            "x": 21,
            "y": 6
        },
        {
            "x": 22,
            "y": 6
        },
        {
            "x": 1,
            "y": 7
        },
        {
            "x": 3,
            "y": 7
        },
        {
            "x": 2,
            "y": 8
        },
        {
            "x": 2,
            "y": 9
        },
        {
            "x": 8,
            "y": 9
        },
        {
            "x": 19,
            "y": 9
        },
        {
            "x": 29,
            "y": 9
        },
        {
            "x": 30,
            "y": 9
        },
        {
            "x": 7,
            "y": 10
        },
        {
            "x": 9,
            "y": 10
        },
        {
            "x": 18,
            "y": 10
        },
        {
            "x": 19,
            "y": 10
        },
        {
            "x": 29,
            "y": 10
        },
        {
            "x": 30,
            "y": 10
        },
        {
            "x": 8,
            "y": 11
        },
        {
            "x": 16,
            "y": 11
        },
        {
            "x": 17,
            "y": 11
        },
        {
            "x": 14,
            "y": 12
        },
        {
            "x": 15,
            "y": 12
        },
        {
            "x": 18,
            "y": 12
        },
        {
            "x": 18,
            "y": 13
        },
        {
            "x": 21,
            "y": 13
        },
        {
            "x": 20,
            "y": 14
        },
        {
            "x": 14,
            "y": 15
        },
        {
            "x": 16,
            "y": 15
        },
        {
            "x": 20,
            "y": 15
        },
        {
            "x": 15,
            "y": 16
        },
        {
            "x": 16,
            "y": 16
        },
        {
            "x": 17,
            "y": 16
        },
        {
            "x": 22,
            "y": 16
        },
        {
            "x": 0,
            "y": 18
        },
        {
            "x": 1,
            "y": 18
        },
        {
            "x": 0,
            "y": 19
        },
        {
            "x": 1,
            "y": 19
        },
        {
            "x": 36,
            "y": 25
        },
        {
            "x": 37,
            "y": 25
        },
        {
            "x": 36,
            "y": 26
        },
        {
            "x": 37,
            "y": 26
        },
        {
            "x": 15,
            "y": 28
        },
        {
            "x": 20,
            "y": 28
        },
        {
            "x": 21,
            "y": 28
        },
        {
            "x": 22,
            "y": 28
        },
        {
            "x": 17,
            "y": 29
        },
        {
            "x": 21,
            "y": 29
        },
        {
            "x": 23,
            "y": 29
        },
        {
            "x": 17,
            "y": 30
        },
        {
            "x": 16,
            "y": 31
        },
        {
            "x": 19,
            "y": 31
        },
        {
            "x": 19,
            "y": 32
        },
        {
            "x": 22,
            "y": 32
        },
        {
            "x": 23,
            "y": 32
        },
        {
            "x": 20,
            "y": 33
        },
        {
            "x": 21,
            "y": 33
        },
        {
            "x": 29,
            "y": 33
        },
        {
            "x": 7,
            "y": 34
        },
        {
            "x": 8,
            "y": 34
        },
        {
            "x": 18,
            "y": 34
        },
        {
            "x": 19,
            "y": 34
        },
        {
            "x": 28,
            "y": 34
        },
        {
            "x": 30,
            "y": 34
        },
        {
            "x": 7,
            "y": 35
        },
        {
            "x": 8,
            "y": 35
        },
        {
            "x": 18,
            "y": 35
        },
        {
            "x": 29,
            "y": 35
        },
        {
            "x": 15,
            "y": 38
        },
        {
            "x": 16,
            "y": 38
        },
        {
            "x": 16,
            "y": 39
        },
        {
            "x": 13,
            "y": 40
        },
        {
            "x": 14,
            "y": 40
        },
        {
            "x": 15,
            "y": 40
        },
        {
            "x": 13,
            "y": 41
        }
    ]
}